mass_ping.py
mass_ping-2.dist-info/METADATA
mass_ping-2.dist-info/WHEEL
mass_ping-2.dist-info/top_level.txt
mass_ping-2.dist-info/RECORD
