Metadata-Version: 2.1
Name: mass-ping
Version: 2
Summary: A threaded ICMP ping using /bin/ping, ping.exe.
Home-page: https://github.com/YUChoe/mass_ping
Author: Tom YU Choe
Author-email: yonguk.choe@gmail.com
License: MIT
Platform: UNKNOWN
Classifier: Development Status :: 4 - Beta
Classifier: Intended Audience :: System Administrators
Classifier: Programming Language :: Python :: 3
Classifier: Programming Language :: Python :: 3.4
Classifier: Programming Language :: Python :: 3.6
Classifier: License :: OSI Approved :: MIT License
Classifier: Operating System :: POSIX :: Linux
